averag_mult_three/__init__.py
averag_mult_three/average_three_numb/__init__.py
averag_mult_three/average_three_numb/average_calculation.py
averag_mult_three/multiplication_three_numb/__init__.py
averag_mult_three/multiplication_three_numb/multiplication_calculation.py
averag_mult_three-0.0.1.dist-info/METADATA
averag_mult_three-0.0.1.dist-info/WHEEL
averag_mult_three-0.0.1.dist-info/top_level.txt
averag_mult_three-0.0.1.dist-info/RECORD
