Metadata-Version: 2.1
Name: averag_mult_three
Version: 0.0.1
Summary: Testando a criação de pacote em Python
Home-page: https://github.com/dimitrimarinho/averag_mult_three
Author: Dimitri Marinho
Author-email: dimitri.santana.marinho@gmail.com
License: UNKNOWN
Platform: UNKNOWN
Requires-Python: >=3.8
